AES/aesfiles/aes_controller.v
module aes_controller(
    input clk,
    input rst,
    input start,
    input round_done,
    output reg [3:0] round,
    output reg done
);

    reg active;

    always @(posedge clk or posedge rst) begin
        if (rst) begin
            round  <= 0;
            done   <= 0;
            active <= 0;
        end 

        // Start encryption
        else if (start && !active) begin
            active <= 1;
            round  <= 0;
            done   <= 0;
        end 

        // Active encryption
        else if (active) begin

            // Move to next round ONLY when round_done pulse comes
            if (round_done) begin

                if (round == 4'd14) begin
                    // Last round completed
                    done   <= 1;
                    active <= 0;
                end 
                else begin
                    round <= round + 1;
                end

            end
        end

        //  clear done after 1 cycle (clean pulse)
        else begin
            done <= 0;
        end
    end

endmodule

AES/aesfiles/tb_aes_controller.sv
`timescale 1ns/1ps

module tb_aes_controller;

    // 1. Declare testbench signals
    reg clk;
    reg rst;
    reg start;
    reg round_done;
    
    wire [3:0] round;
    wire done;

    // 2. Instantiate the Unit Under Test (UUT)
    aes_controller uut (
        .clk(clk),
        .rst(rst),
        .start(start),
        .round_done(round_done),
        .round(round),
        .done(done)
    );

    // 3. Clock Generation (100MHz)
    initial clk = 0;
    always #5 clk = ~clk;

    // 4. Test Stimulus Process
    initial begin
        $dumpfile("aes_controller.vcd");
        $dumpvars(0, tb_aes_controller);

        $display("--- Starting aes_controller Testbench ---");

        // Step 1: Initialize values and Hold Reset
        rst = 1;
        start = 0;
        round_done = 0;

        @(posedge clk);
        @(posedge clk);
        
        // Release Reset
        rst = 0;
        @(posedge clk);

        // Step 2: Send Start Pulse
        $display("[Time %0t] Sending START pulse...", $time);
        start = 1;
        @(posedge clk);
        start = 0;

        // Step 3: Simulate the 15 AES Rounds (0 through 14)
        for (integer i = 0; i <= 14; i = i + 1) begin
            // Wait 2 clock cycles to pretend the pipeline is "doing math"
            @(posedge clk);
            @(posedge clk);
            
            // Pulse round_done to tell controller to move forward
            $display("[Time %0t] Controller is currently at Round: %d", $time, round);
            round_done = 1;
            @(posedge clk);
            round_done = 0;
        end

        // Step 4: Verify the DONE signal
        @(posedge clk); // Allow state to update
        if (done)
             $display("[PASS] SUCCESS! Controller issued DONE pulse after Round 14!");
        else
             $display("[FAIL] Controller did not issue DONE pulse!");
             
        @(posedge clk);
        @(posedge clk);
        $display("--- Testbench Complete ---");
        $finish;
    end

endmodule

AES/aesfiles/aes_controller.vcd
$date
	Fri Apr  3 15:30:01 2026
$end
$version
	Icarus Verilog
$end
$timescale
	1ps
$end
$scope module tb_aes_controller $end
$var wire 4 ! round [3:0] $end
$var wire 1 " done $end
$var reg 1 # clk $end
$var reg 1 $ round_done $end
$var reg 1 % rst $end
$var reg 1 & start $end
$scope module uut $end
$var wire 1 # clk $end
$var wire 1 $ round_done $end
$var wire 1 % rst $end
$var wire 1 & start $end
$var reg 1 ' active $end
$var reg 1 " done $end
$var reg 4 ( round [3:0] $end
$upscope $end
$scope begin $ivl_for_loop0 $end
$var integer 32 ) i [31:0] $end
$upscope $end
$upscope $end
$enddefinitions $end
$comment Show the parameter values. $end
$dumpall
$end
#0
$dumpvars
bx )
b0 (
0'
0&
1%
0$
0#
0"
b0 !
$end
#5000
1#
#10000
0#
#15000
0%
1#
#20000
0#
#25000
1'
1&
1#
#30000
0#
#35000
b0 )
0&
1#
#40000
0#
#45000
1#
#50000
0#
#55000
b1 !
b1 (
1$
1#
#60000
0#
#65000
b1 )
0$
1#
#70000
0#
#75000
1#
#80000
0#
#85000
b10 !
b10 (
1$
1#
#90000
0#
#95000
b10 )
0$
1#
#100000
0#
#105000
1#
#110000
0#
#115000
b11 !
b11 (
1$
1#
#120000
0#
#125000
b11 )
0$
1#
#130000
0#
#135000
1#
#140000
0#
#145000
b100 !
b100 (
1$
1#
#150000
0#
#155000
b100 )
0$
1#
#160000
0#
#165000
1#
#170000
0#
#175000
b101 !
b101 (
1$
1#
#180000
0#
#185000
b101 )
0$
1#
#190000
0#
#195000
1#
#200000
0#
#205000
b110 !
b110 (
1$
1#
#210000
0#
#215000
b110 )
0$
1#
#220000
0#
#225000
1#
#230000
0#
#235000
b111 !
b111 (
1$
1#
#240000
0#
#245000
b111 )
0$
1#
#250000
0#
#255000
1#
#260000
0#
#265000
b1000 !
b1000 (
1$
1#
#270000
0#
#275000
b1000 )
0$
1#
#280000
0#
#285000
1#
#290000
0#
#295000
b1001 !
b1001 (
1$
1#
#300000
0#
#305000
b1001 )
0$
1#
#310000
0#
#315000
1#
#320000
0#
#325000
b1010 !
b1010 (
1$
1#
#330000
0#
#335000
b1010 )
0$
1#
#340000
0#
#345000
1#
#350000
0#
#355000
b1011 !
b1011 (
1$
1#
#360000
0#
#365000
b1011 )
0$
1#
#370000
0#
#375000
1#
#380000
0#
#385000
b1100 !
b1100 (
1$
1#
#390000
0#
#395000
b1100 )
0$
1#
#400000
0#
#405000
1#
#410000
0#
#415000
b1101 !
b1101 (
1$
1#
#420000
0#
#425000
b1101 )
0$
1#
#430000
0#
#435000
1#
#440000
0#
#445000
b1110 !
b1110 (
1$
1#
#450000
0#
#455000
b1110 )
0$
1#
#460000
0#
#465000
1#
#470000
0#
#475000
0'
1"
1$
1#
#480000
0#
#485000
0"
b1111 )
0$
1#
